aiohttp_cors/__about__.py
aiohttp_cors/__init__.py
aiohttp_cors/abc.py
aiohttp_cors/cors_config.py
aiohttp_cors/mixin.py
aiohttp_cors/preflight_handler.py
aiohttp_cors/py.typed
aiohttp_cors/resource_options.py
aiohttp_cors/urldispatcher_router_adapter.py
alt_aiohttp_cors-0.7.2.dist-info/LICENSE
alt_aiohttp_cors-0.7.2.dist-info/METADATA
alt_aiohttp_cors-0.7.2.dist-info/WHEEL
alt_aiohttp_cors-0.7.2.dist-info/top_level.txt
alt_aiohttp_cors-0.7.2.dist-info/RECORD
