Metadata-Version: 2.1
Name: alt-aiohttp-cors
Version: 0.7.2
Summary: CORS support for aiohttp
Home-page: https://github.com/aio-libs/aiohttp-cors
Author: Vladimir Rutsky and aio-libs team
Author-email: vladimir@rutsky.org
License: Apache License, Version 2.0
Classifier: License :: OSI Approved :: Apache Software License
Classifier: Intended Audience :: Developers
Classifier: Programming Language :: Python
Classifier: Programming Language :: Python :: 3
Classifier: Programming Language :: Python :: 3.4
Classifier: Programming Language :: Python :: 3.5
Classifier: Programming Language :: Python :: 3.6
Classifier: Topic :: Software Development :: Libraries
Classifier: Topic :: Internet :: WWW/HTTP
Classifier: Framework :: AsyncIO
Classifier: Operating System :: MacOS :: MacOS X
Classifier: Operating System :: Microsoft :: Windows
Classifier: Operating System :: POSIX
Classifier: Development Status :: 3 - Alpha
Classifier: Framework :: aiohttp
License-File: LICENSE
Requires-Dist: aiohttp>=3.1
Requires-Dist: typing; python_version < "3.5"
